Metadata-Version: 2.1
Name: bimmm
Version: 0.0.2
Summary: Package that makes it a bit easier to visualize and analyse Marketing Mix Models
Home-page: UNKNOWN
Author: Simon Teggelaar
Author-email: simonteggelaar@gmail.com
License: MIT
Platform: UNKNOWN
Classifier: Programming Language :: Python :: 3
Classifier: License :: OSI Approved :: MIT License
Classifier: Operating System :: OS Independent
